fast_tsp/_core.cpython-313-darwin.so
fast_tsp/__init__.py
fast_tsp-0.1.5.dist-info/RECORD
fast_tsp-0.1.5.dist-info/WHEEL
fast_tsp-0.1.5.dist-info/top_level.txt
fast_tsp-0.1.5.dist-info/METADATA
fast_tsp-0.1.5.dist-info/licenses/LICENSE
