Metadata-Version: 2.4
Name: fast_tsp
Version: 0.1.5
Summary: A fast TSP solver with Python bindings
Home-page: http://github.com/shmulvad/fast-tsp
Author: Soeren Mulvad
Author-email: shmulvad@gmail.com
License: MIT
Requires-Python: >=3.10
License-File: LICENSE
Requires-Dist: numpy>=1.0.0
Provides-Extra: test
Requires-Dist: pytest; extra == "test"
Requires-Dist: numpy; extra == "test"
Provides-Extra: docs
Requires-Dist: sphinx; extra == "docs"
Requires-Dist: sphinx-rtd-theme; extra == "docs"
Requires-Dist: sphinx-autodoc-typehints; extra == "docs"
Dynamic: author
Dynamic: author-email
Dynamic: description
Dynamic: description-content-type
Dynamic: home-page
Dynamic: license
Dynamic: license-file
Dynamic: provides-extra
Dynamic: requires-dist
Dynamic: requires-python
Dynamic: summary
